PyMLBStats/StrikeZone.py
PyMLBStats/__init__.py
PyMLBStats/baseball.py
PyMLBStats/constants.py
PyMLBStats/paths.py
PyMLBStats/test.py
PyMLBStats/version.py
PyMLBStats-0.0.1.dist-info/LICENSE
PyMLBStats-0.0.1.dist-info/METADATA
PyMLBStats-0.0.1.dist-info/WHEEL
PyMLBStats-0.0.1.dist-info/top_level.txt
PyMLBStats-0.0.1.dist-info/RECORD
