Metadata-Version: 2.1
Name: PyMLBStats
Version: 0.0.1
Summary: Python baseball
Home-page: https://github.com/Thexumaker/PyBaseball/tree/master/pybaseball
Author: David Xu
Author-email: thexumaker@berkeley.edu
License: UNKNOWN
Platform: UNKNOWN
Classifier: Programming Language :: Python :: 3
Classifier: License :: OSI Approved :: MIT License
Classifier: Operating System :: OS Independent
